.gitignore
LICENSE
MANIFEST.in
README.rst
setup.py
django_herokuapp.egg-info/PKG-INFO
django_herokuapp.egg-info/SOURCES.txt
django_herokuapp.egg-info/dependency_links.txt
django_herokuapp.egg-info/entry_points.txt
django_herokuapp.egg-info/requires.txt
django_herokuapp.egg-info/top_level.txt
herokuapp/__init__.py
herokuapp/commands.py
herokuapp/env.py
herokuapp/introspection.py
herokuapp/middleware.py
herokuapp/settings.py
herokuapp/tests.py
herokuapp/bin/__init__.py
herokuapp/bin/herokuapp_startproject.py
herokuapp/management/__init__.py
herokuapp/management/commands/__init__.py
herokuapp/management/commands/base.py
herokuapp/management/commands/heroku_audit.py
herokuapp/management/commands/heroku_deploy.py
herokuapp/project_template/.gitignore
herokuapp/project_template/.slugignore
herokuapp/project_template/deploy.sh
herokuapp/project_template/manage.py
herokuapp/project_template/project_name/__init__.py
herokuapp/project_template/project_name/urls.py
herokuapp/project_template/project_name/wsgi.py
herokuapp/project_template/project_name/apps/__init__.py
herokuapp/project_template/project_name/settings/.gitignore
herokuapp/project_template/project_name/settings/__init__.py
herokuapp/project_template/project_name/settings/local.py
herokuapp/project_template/project_name/settings/production.py
herokuapp/project_template/project_name/static/js/.gitignore
herokuapp/project_template/project_name/templates/.gitignore