Metadata-Version: 1.1
Name: django-herokuapp
Version: 0.9.17
Summary: A set of utilities and a project template for running Django sites on heroku.
Home-page: https://github.com/etianen/django-herokuapp
Author: Dave Hall
Author-email: dave@etianen.com
License: BSD
Platform: UNKNOWN
Classifier: Development Status :: 4 - Beta
Classifier: Environment :: Web Environment
Classifier: Intended Audience :: Developers
Classifier: License :: OSI Approved :: BSD License
Classifier: Operating System :: OS Independent
Classifier: Programming Language :: Python
Classifier: Framework :: Django
